qwrapper/__init__.py
qwrapper/qemumachine.py
qwrapper/x86/__init__.py
qwrapper/x86/x86machine.py
qwrapper/x86/utils/__init__.py
qwrapper/x86/utils/debugging.py
qwrapper/x86/utils/machinestate.py
qwrapper/x86/utils/memory.py
qwrapper/x86/utils/registers.py
qwrapper-0.1.19.dist-info/LICENSE
qwrapper-0.1.19.dist-info/METADATA
qwrapper-0.1.19.dist-info/WHEEL
qwrapper-0.1.19.dist-info/top_level.txt
qwrapper-0.1.19.dist-info/RECORD
