Metadata-Version: 2.1
Name: qwrapper
Version: 0.1.19
Summary: A QEMU wrapper for Python
Author-email: Daniel Dybing <danieldy@uia.no>, Ali Sirvanovitsj Ismailov <alisi18@uia.no>, Sirén Elise Lund Lohre <selohre@uia.no>
License: MIT License
Classifier: Programming Language :: Python :: 3
Classifier: License :: OSI Approved :: MIT License
Requires-Python: >=3.7
License-File: LICENSE
Requires-Dist: pygdbmi
Requires-Dist: qemu.qmp
